symsynd-3.2.0.dist-info/WHEEL
symsynd-3.2.0.dist-info/DESCRIPTION.rst
symsynd-3.2.0.dist-info/METADATA
symsynd-3.2.0.dist-info/RECORD
symsynd-3.2.0.dist-info/top_level.txt
symsynd-3.2.0.dist-info/metadata.json
symsynd/_demangler.so
symsynd/libdebug.py
symsynd/demangle.py
symsynd/__init__.py
symsynd/_symbolizer.py
symsynd/libsymbolizer.py
symsynd/_libsymbolizer.so
symsynd/_debug.py
symsynd/images.py
symsynd/_compat.py
symsynd/exceptions.py
symsynd/heuristics.py
symsynd/_libdebug.so
symsynd/symbolizer.py
symsynd/utils.py
