Metadata-Version: 2.0
Name: symsynd
Version: 3.2.0
Summary: Helps symbolicating crash dumps.
Home-page: http://github.com/getsentry/symsynd
Author: Sentry
Author-email: hello@getsentry.com
License: BSD
Platform: any
Classifier: Intended Audience :: Developers
Classifier: License :: OSI Approved :: BSD License
Classifier: Operating System :: OS Independent
Classifier: Programming Language :: Python
Classifier: Topic :: Internet :: WWW/HTTP :: Dynamic Content
Classifier: Topic :: Software Development :: Libraries :: Python Modules
Requires-Dist: cffi (>=1.0.0)
